condolence_models/__init__.py
condolence_models/common.py
condolence_models/condolence_classifier.py
condolence_models/distress_classifier.py
condolence_models/empathy_classifier.py
condolence_models/bert_classifier/__init__.py
condolence_models/bert_classifier/classifier.py
condolence_models/bert_classifier/utils.py
condolence_models-1.0.0.dist-info/LICENSE
condolence_models-1.0.0.dist-info/METADATA
condolence_models-1.0.0.dist-info/WHEEL
condolence_models-1.0.0.dist-info/top_level.txt
condolence_models-1.0.0.dist-info/RECORD
