Metadata-Version: 2.1
Name: condolence-models
Version: 1.0.0
Summary: Detecting condolence, distress, and empathy in text
Home-page: UNKNOWN
Author: Naitian Zhou
Author-email: naitian@umich.edu
License: UNKNOWN
Platform: UNKNOWN
Requires-Python: >=3.6
Requires-Dist: torch
Requires-Dist: pytorch-transformers
Requires-Dist: markdown
Requires-Dist: beautifulsoup4
Requires-Dist: numpy
Requires-Dist: tqdm
Requires-Dist: simpletransformers
Requires-Dist: pandas
